{
  "date": "2020-10-20T09:17:48.006Z",
  "incident": "logee-user:dev, logee-order:dev, koja-wsdl:dev is down.",
  "status": "error",
  "services": [
    {
      "desc": "Smart Contract Dev",
      "env": "dev",
      "status": "ok",
      "incidents": [
        {
          "date": "2020-09-30T23:33:29.703Z",
          "status": "ok"
        },
        {
          "date": "2020-09-30T23:26:13.789Z",
          "status": "error"
        },
        {
          "date": "2020-09-18T08:57:28.059Z",
          "status": "ok"
        },
        {
          "date": "2020-09-18T08:50:31.240Z",
          "status": "error"
        },
        {
          "date": "2020-09-18T03:31:27.782Z",
          "status": "ok"
        }
      ]
    },
    {
      "desc": "logee-truck",
      "env": "dev",
      "status": "ok",
      "incidents": [
        {
          "date": "2020-10-19T07:43:16.731Z",
          "status": "ok"
        },
        {
          "date": "2020-10-19T07:36:40.733Z",
          "status": "error"
        },
        {
          "date": "2020-10-19T07:26:51.242Z",
          "status": "ok"
        },
        {
          "date": "2020-10-19T07:10:28.066Z",
          "status": "error"
        },
        {
          "date": "2020-10-15T13:53:18.250Z",
          "status": "ok"
        },
        {
          "date": "2020-10-15T13:46:14.469Z",
          "status": "error"
        }
      ]
    },
    {
      "desc": "logee-billing",
      "env": "dev",
      "status": "ok",
      "incidents": [
        {
          "date": "2020-10-15T14:37:30.375Z",
          "status": "ok"
        },
        {
          "date": "2020-10-15T14:27:16.506Z",
          "status": "error"
        },
        {
          "date": "2020-10-15T13:31:54.717Z",
          "status": "ok"
        },
        {
          "date": "2020-10-15T13:23:47.973Z",
          "status": "error"
        },
        {
          "date": "2020-10-15T11:58:42.192Z",
          "status": "ok"
        },
        {
          "date": "2020-10-15T11:38:11.436Z",
          "status": "error"
        }
      ]
    },
    {
      "desc": "logee-cargo",
      "env": "dev",
      "status": "ok",
      "incidents": [
        {
          "date": "2020-10-16T01:06:48.812Z",
          "status": "ok"
        },
        {
          "date": "2020-10-15T23:58:56.806Z",
          "status": "error"
        },
        {
          "date": "2020-10-15T14:37:30.340Z",
          "status": "ok"
        },
        {
          "date": "2020-10-15T14:27:16.506Z",
          "status": "error"
        },
        {
          "date": "2020-10-15T13:00:04.724Z",
          "status": "ok"
        },
        {
          "date": "2020-10-15T12:53:29.202Z",
          "status": "error"
        }
      ]
    },
    {
      "desc": "logee-order",
      "env": "dev",
      "status": "error",
      "incidents": [
        {
          "date": "2020-10-20T09:17:44.071Z",
          "status": "error"
        },
        {
          "date": "2020-10-19T07:26:51.290Z",
          "status": "ok"
        },
        {
          "date": "2020-10-19T07:10:28.065Z",
          "status": "error"
        },
        {
          "date": "2020-10-17T10:25:56.989Z",
          "status": "ok"
        },
        {
          "date": "2020-10-17T10:05:53.934Z",
          "status": "error"
        },
        {
          "date": "2020-10-15T13:46:11.430Z",
          "status": "ok"
        }
      ]
    },
    {
      "desc": "logee-user",
      "env": "dev",
      "status": "error",
      "incidents": [
        {
          "date": "2020-10-20T09:17:44.138Z",
          "status": "error"
        },
        {
          "date": "2020-10-18T11:44:05.328Z",
          "status": "ok"
        },
        {
          "date": "2020-10-18T11:37:05.650Z",
          "status": "error"
        },
        {
          "date": "2020-10-17T15:48:06.469Z",
          "status": "ok"
        },
        {
          "date": "2020-10-17T15:41:14.509Z",
          "status": "error"
        },
        {
          "date": "2020-10-15T13:46:10.664Z",
          "status": "ok"
        }
      ]
    },
    {
      "desc": "koja-wsdl",
      "env": "prod",
      "status": "ok",
      "incidents": [
        {
          "date": "2020-10-14T08:00:20.897Z",
          "status": "ok"
        },
        {
          "date": "2020-10-14T05:37:01.435Z",
          "status": "error"
        },
        {
          "date": "2020-10-11T17:27:29.191Z",
          "status": "ok"
        },
        {
          "date": "2020-10-11T16:26:55.117Z",
          "status": "error"
        },
        {
          "date": "2020-10-07T08:09:49.689Z",
          "status": "ok"
        },
        {
          "date": "2020-10-07T07:55:07.103Z",
          "status": "error"
        }
      ]
    },
    {
      "desc": "logee-minio",
      "env": "dev",
      "status": "ok",
      "incidents": [
        {
          "date": "2020-10-18T11:44:06.586Z",
          "status": "ok"
        },
        {
          "date": "2020-10-18T11:37:05.731Z",
          "status": "error"
        },
        {
          "date": "2020-10-17T19:43:50.690Z",
          "status": "ok"
        },
        {
          "date": "2020-10-17T19:36:58.400Z",
          "status": "error"
        },
        {
          "date": "2020-10-17T15:41:13.628Z",
          "status": "ok"
        },
        {
          "date": "2020-10-17T15:32:34.067Z",
          "status": "error"
        }
      ]
    },
    {
      "desc": "Gitlab",
      "env": "prod",
      "status": "ok",
      "incidents": [
        {
          "date": "2020-10-20T04:29:49.159Z",
          "status": "ok"
        },
        {
          "date": "2020-10-20T04:11:45.413Z",
          "status": "error"
        },
        {
          "date": "2020-10-18T23:33:39.022Z",
          "status": "ok"
        },
        {
          "date": "2020-10-18T23:24:49.096Z",
          "status": "error"
        },
        {
          "date": "2020-10-18T13:51:59.321Z",
          "status": "ok"
        },
        {
          "date": "2020-10-18T13:44:55.349Z",
          "status": "error"
        }
      ]
    },
    {
      "desc": "koja-wsdl",
      "env": "dev",
      "status": "error",
      "incidents": [
        {
          "date": "2020-09-18T03:31:32.638Z",
          "status": "error"
        }
      ]
    }
  ]
}